pyscientificpdfparser/__init__.py
pyscientificpdfparser/cli.py
pyscientificpdfparser/core.py
pyscientificpdfparser/dla.py
pyscientificpdfparser/llm_refinement.py
pyscientificpdfparser/models.py
pyscientificpdfparser/ocr.py
pyscientificpdfparser/output.py
pyscientificpdfparser/preprocessing.py
pyscientificpdfparser/sectioning.py
pyscientificpdfparser/tsr.py
pyscientificpdfparser-0.2.0.dist-info/METADATA
pyscientificpdfparser-0.2.0.dist-info/WHEEL
pyscientificpdfparser-0.2.0.dist-info/entry_points.txt
pyscientificpdfparser-0.2.0.dist-info/licenses/LICENSE
pyscientificpdfparser-0.2.0.dist-info/licenses/NOTICE
pyscientificpdfparser-0.2.0.dist-info/RECORD
