Metadata-Version: 2.4
Name: pyscientificpdfparser
Version: 0.2.0
Summary: A Python package to parse scientific PDF documents into structured Markdown.
License: Apache-2.0
License-File: LICENSE
License-File: NOTICE
Keywords: pdf,parser,scientific,document,ai,llm,markdown,ocr
Author: Gowtham Rao
Author-email: rao@ohdsi.org
Requires-Python: >=3.10,<4.0
Classifier: Development Status :: 4 - Beta
Classifier: Intended Audience :: Science/Research
Classifier: License :: OSI Approved :: Apache Software License
Classifier: Programming Language :: Python :: 3
Classifier: Programming Language :: Python :: 3.10
Classifier: Programming Language :: Python :: 3.11
Classifier: Programming Language :: Python :: 3.12
Classifier: Programming Language :: Python :: 3.13
Classifier: Programming Language :: Python :: 3.14
Classifier: Topic :: Scientific/Engineering :: Information Analysis
Provides-Extra: llm
Provides-Extra: ml
Requires-Dist: click (>=8.1.7,<9.0.0)
Requires-Dist: instructor (>=1.3.2,<2.0.0) ; extra == "llm"
Requires-Dist: langchain-core (>=0.3.0,<0.4.0) ; extra == "llm"
Requires-Dist: langchain-openai (>=0.2.0,<0.3.0) ; extra == "llm"
Requires-Dist: opencv-python-headless (>=4.9.0.80,<5.0.0.0)
Requires-Dist: pillow (>=10.3.0,<11.0.0)
Requires-Dist: py-markdown-table (>=1.3.0,<2.0.0)
Requires-Dist: pydantic (>=2.7.1,<3.0.0)
Requires-Dist: pymupdf (>=1.24.1,<2.0.0)
Requires-Dist: pytesseract (>=0.3.10,<0.4.0)
Requires-Dist: tenacity (>=8.2.3,<9.0.0)
Requires-Dist: torch (>=2.3.1,<3.0.0) ; extra == "ml"
Requires-Dist: transformers (>=4.40.0,<5.0.0) ; extra == "ml"
Project-URL: Repository, https://github.com/Gowtham-Rao/pyScientificPdfParser
